cardamom_ai/__init__.py
cardamom_ai/deploy.py
cardamom_ai/serialize_sklearn.py
cardamom_ai-0.0.5.dist-info/LICENSE
cardamom_ai-0.0.5.dist-info/METADATA
cardamom_ai-0.0.5.dist-info/WHEEL
cardamom_ai-0.0.5.dist-info/top_level.txt
cardamom_ai-0.0.5.dist-info/RECORD
