Metadata-Version: 2.1
Name: cardamom-ai
Version: 0.0.5
Home-page: https://cardamom.ai
Author: Cardamom AI
Author-email: sales@cardamom.ai
License: AGPL
Keywords: cardamom,ml,deployment
Requires-Python: <4,>=3.7
License-File: LICENSE
Requires-Dist: numpy
Requires-Dist: requests
Requires-Dist: scikit-learn
Requires-Dist: pandas
Provides-Extra: test
Requires-Dist: pytest ; extra == 'test'
Requires-Dist: coverage ; extra == 'test'
